sarcharts/__init__.py
sarcharts/bin/__init__.py
sarcharts/html/__init__.py
sarcharts/html/css/__init__.py
sarcharts/html/css/sarcharts.css
sarcharts/html/css/ul-select.css
sarcharts/html/img/__init__.py
sarcharts/html/img/chevron.svg
sarcharts/html/js/__init__.py
sarcharts/html/js/chart.umd.js
sarcharts/html/js/chartjs-adapter-date-fns.bundle.min.js
sarcharts/html/js/chartjs-plugin-annotation.min.js
sarcharts/html/js/chartjs-plugin-zoom.min.js
sarcharts/html/js/hammer.min.js
sarcharts/html/js/jquery.js
sarcharts/html/js/ul-select.js
sarcharts/lib/__init__.py
sarcharts/lib/chartjs.py
sarcharts/lib/events.py
sarcharts/lib/metrics.py
sarcharts/lib/progressbar.py
sarcharts/lib/sadf.py
sarcharts/lib/util.py
sarcharts/templates/__init__.py
sarcharts/templates/chart.html
sarcharts/templates/header.html
sarcharts-0.3.4.data/scripts/__init__.py
sarcharts-0.3.4.dist-info/AUTHORS
sarcharts-0.3.4.dist-info/LICENSE
sarcharts-0.3.4.dist-info/METADATA
sarcharts-0.3.4.dist-info/WHEEL
sarcharts-0.3.4.dist-info/entry_points.txt
sarcharts-0.3.4.dist-info/top_level.txt
sarcharts-0.3.4.dist-info/RECORD
