Metadata-Version: 2.2
Name: sarcharts
Version: 0.3.4
Summary: SarCharts gets sysstat files from provided sarfilespaths
Home-page: https://github.com/pafernanr/sarcharts
Author: Pablo Fernández Rodríguez
License: GPLv3
Keywords: sysstat sar sadf
Classifier: Intended Audience :: Information Technology
Classifier: Intended Audience :: System Administrators
Classifier: License :: OSI Approved :: GNU General Public License v3 (GPLv3)
Classifier: Operating System :: POSIX :: Linux
Classifier: Programming Language :: Python
Classifier: Programming Language :: Python :: 3
License-File: LICENSE
License-File: AUTHORS
Dynamic: author
Dynamic: classifier
Dynamic: description
Dynamic: description-content-type
Dynamic: home-page
Dynamic: keywords
Dynamic: license
Dynamic: summary
